py_weatherdataai/__init__.py
py_weatherdataai/client.py
py_weatherdataai-0.1.0.dist-info/METADATA
py_weatherdataai-0.1.0.dist-info/WHEEL
py_weatherdataai-0.1.0.dist-info/top_level.txt
py_weatherdataai-0.1.0.dist-info/RECORD
